README.md
setup.cfg
setup.py
gym_checkerboard/__init__.py
gym_checkerboard/checkerboard.py
gym_checkerboard/checkerboard_simulator.py
gym_checkerboard/tests/__init__.py
gym_checkerboard/tests/test_checkerboard.py
gym_checkerboard/tests/test_checkerboard_simulator.py
gym_corridor/__init__.py
gym_corridor/corridor.py
gym_corridor/tests/__init__.py
gym_corridor/tests/test_corridor.py
gym_grid/__init__.py
gym_grid/grid.py
gym_grid/tests/__init__.py
gym_grid/tests/test_grid.py
gym_handeye/__init__.py
gym_handeye/handeye.py
gym_handeye/handeye_simulator.py
gym_handeye/tests/__init__.py
gym_handeye/tests/test_handeye.py
gym_handeye/tests/test_handeye_simulator.py
gym_handeye/utils/__init__.py
gym_handeye/utils/utils.py
gym_maze/__init__.py
gym_maze/maze.py
gym_maze/envs/Maze4.py
gym_maze/envs/Maze5.py
gym_maze/envs/Maze6.py
gym_maze/envs/MazeF1.py
gym_maze/envs/MazeF2.py
gym_maze/envs/MazeF3.py
gym_maze/envs/MazeF4.py
gym_maze/envs/Woods1.py
gym_maze/envs/Woods14.py
gym_maze/envs/__init__.py
gym_maze/envs/abstract_maze.py
gym_maze/tests/__init__.py
gym_maze/tests/test_maze.py
gym_maze/tests/test_utils.py
gym_maze/utils/__init__.py
gym_maze/utils/utils.py
gym_multiplexer/__init__.py
gym_multiplexer/boolean_multiplexer.py
gym_multiplexer/multiplexer.py
gym_multiplexer/real_multiplexer.py
gym_multiplexer/tests/__init__.py
gym_multiplexer/tests/test_boolean_multiplexer.py
gym_multiplexer/tests/test_real_multiplexer.py
gym_multiplexer/tests/test_utils.py
gym_multiplexer/utils/__init__.py
gym_multiplexer/utils/utils.py
gym_real_value_toy/__init__.py
gym_real_value_toy/toy_env.py
gym_real_value_toy/orthogonal/__init__.py
gym_real_value_toy/orthogonal/x_axis_boundary.py
gym_real_value_toy/tests/__init__.py
gym_real_value_toy/tests/orthogonal/__init__.py
gym_real_value_toy/tests/orthogonal/test_x_axis_boundary.py
gym_taxi_goal/__init__.py
gym_taxi_goal/taxi_goal.py
gym_taxi_goal/tests/__init__.py
gym_taxi_goal/tests/test_taxi_goal.py
parrotprediction_openai_envs.egg-info/PKG-INFO
parrotprediction_openai_envs.egg-info/SOURCES.txt
parrotprediction_openai_envs.egg-info/dependency_links.txt
parrotprediction_openai_envs.egg-info/not-zip-safe
parrotprediction_openai_envs.egg-info/requires.txt
parrotprediction_openai_envs.egg-info/top_level.txt