Metadata-Version: 1.0
Name: parrotprediction-openai-envs
Version: 2.1.0
Summary: Custom environments for OpenAI Gym
Home-page: https://github.com/ParrotPrediction/openai-envs
Author: Parrot Prediction Ltd.
Author-email: nkozlowski@protonmail.com
License: MIT
Keywords: acs lcs machine-learning reinforcement-learning openai
Platform: UNKNOWN
